odoo/addons/sale_order_invoicing_queued/README.rst
odoo/addons/sale_order_invoicing_queued/__init__.py
odoo/addons/sale_order_invoicing_queued/__manifest__.py
odoo/addons/sale_order_invoicing_queued/i18n/es.po
odoo/addons/sale_order_invoicing_queued/i18n/sale_order_invoicing_queued.pot
odoo/addons/sale_order_invoicing_queued/models/__init__.py
odoo/addons/sale_order_invoicing_queued/models/sale_order.py
odoo/addons/sale_order_invoicing_queued/readme/CONFIGURE.rst
odoo/addons/sale_order_invoicing_queued/readme/CONTRIBUTORS.rst
odoo/addons/sale_order_invoicing_queued/readme/DESCRIPTION.rst
odoo/addons/sale_order_invoicing_queued/readme/INSTALL.rst
odoo/addons/sale_order_invoicing_queued/readme/ROADMAP.rst
odoo/addons/sale_order_invoicing_queued/readme/USAGE.rst
odoo/addons/sale_order_invoicing_queued/static/description/icon.png
odoo/addons/sale_order_invoicing_queued/static/description/index.html
odoo/addons/sale_order_invoicing_queued/tests/__init__.py
odoo/addons/sale_order_invoicing_queued/tests/test_sale_order_invoicing_queued.py
odoo/addons/sale_order_invoicing_queued/views/queue_job_views.xml
odoo/addons/sale_order_invoicing_queued/views/sale_order_views.xml
odoo/addons/sale_order_invoicing_queued/wizards/__init__.py
odoo/addons/sale_order_invoicing_queued/wizards/sale_advance_payment_inv.py
odoo/addons/sale_order_invoicing_queued/wizards/sale_advance_payment_inv_views.xml
odoo11_addon_sale_order_invoicing_queued-11.0.1.1.0.dist-info/METADATA
odoo11_addon_sale_order_invoicing_queued-11.0.1.1.0.dist-info/WHEEL
odoo11_addon_sale_order_invoicing_queued-11.0.1.1.0.dist-info/top_level.txt
odoo11_addon_sale_order_invoicing_queued-11.0.1.1.0.dist-info/RECORD
